LICENSE
README.md
setup.py
pytilesrv/__init__.py
pytilesrv/__main__.py
pytilesrv.egg-info/PKG-INFO
pytilesrv.egg-info/SOURCES.txt
pytilesrv.egg-info/dependency_links.txt
pytilesrv.egg-info/entry_points.txt
pytilesrv.egg-info/requires.txt
pytilesrv.egg-info/top_level.txt